.readthedocs.txt
.requirements-dev.txt
MANIFEST.in
Readme.rst
requirements.txt
setup.py
situation/__init__.py
situation/__meta__.py
situation/debug_app.py
situation/tests.py
situation.egg-info/PKG-INFO
situation.egg-info/SOURCES.txt
situation.egg-info/dependency_links.txt
situation.egg-info/not-zip-safe
situation.egg-info/requires.txt
situation.egg-info/top_level.txt
situation/__pycache__/__init__.cpython-36.pyc
situation/__pycache__/debug_app.cpython-36.pyc
situation/__pycache__/tests.cpython-36.pyc