Metadata-Version: 1.0
Name: situation
Version: 0.1.0rc1
Summary: Situation Modeling Language is an ontology for describing social situations.
Home-page: http://situation.readthedocs.io
Author: Ian Dennis Miller
Author-email: iandennismiller@gmail.com
License: MIT
Platform: UNKNOWN
